simpler_rlp/__init__.py
simpler_rlp/converters.py
simpler_rlp/simpler_rlp.py
simpler_rlp-0.0.1.dist-info/LICENSE
simpler_rlp-0.0.1.dist-info/METADATA
simpler_rlp-0.0.1.dist-info/WHEEL
simpler_rlp-0.0.1.dist-info/top_level.txt
simpler_rlp-0.0.1.dist-info/RECORD
