Metadata-Version: 2.1
Name: simpler-rlp
Version: 0.0.1
Summary: RLP (Recursive Length Prefix) - Encode and decode data structures
Home-page: https://github.com/kristian1108/simple-rlp
Author: Kristian Gaylord
Author-email: krlgaylord@gmail.com
License: MIT Custom
Classifier: License :: OSI Approved :: MIT License
Classifier: Programming Language :: Python :: 3
Requires-Python: >=3.6
License-File: LICENSE
